Lab1/Lab1_gatelevel_UDP.v
primitive or_and (y, a, b, c);
  output y;
  input a, b, c;
  table
    // a  b   c  :  y
       ?  ?   0   :  0;
       0  0   1   :  0;
       1  ?   1   :  1;
       ?  1   1   :  1;
  endtable
endprimitive

module	Lab1_gatelevel_UDP(F, A, B, C, D);
	output F;
	input A,B,C,D;
	wire w1,w2,w3,w4,w5,w6,w7,w8;

	not G1(w1, B);//G1 is "not B"
	or_and(w3, A, w1, C);
	and G4(w4,B,C);
	not G5(w5,D);
	or_and(w7, w4, w5, A);
	or G8(F, w7, w3);
endmodule

Lab1/Lab1_dataflow.v
module	Lab1_dataflow(F, A, B, C, D);
	output F;
	input A,B,C,D;
	wire w1,w2,w3,w4,w5,w6,w7,w8;

	assign w1 = ~B;
	assign w2 = A | w1;
	assign w3 = C & w2;
	assign w4 = B & C;
	assign w5 = ~D;
	assign w6 = w4 | w5;
	assign w7 = A & w6;
	assign F = w3 | w7;
endmodule

Lab1/Lab1_gatelevel.v
module	Lab1_gatelevel(F, A, B, C, D);
	output F;
	input A,B,C,D;
	wire w1,w2,w3,w4,w5,w6,w7,w8;

	not G1(w1, B);//G1 is "not B"
	or G2(w2,A, w1); // A or not B
	and G3(w3,C, w2);
	and G4(w4,B,C);
	not G5(w5,D);
	or G6(w6,w4,w5);
	and G7(w7, A, w6);
	or G8(F, w7, w3);
endmodule

Lab1/t_Lab1.v
module	t_Lab1();
	wire	F1,F2,F3;
	reg		A, B, C, D;
	
	localparam period = 20;  

	Lab1_gatelevel	Gatelevel(F1, A, B, C, D);
	Lab1_dataflow Dataflow(F2, A, B, C, D);
	Lab1_gatelevel_UDP UDP(F3, A, B, C, D);
	//apply inputs one at a time
	initial	begin
		A=0;
		B=0;
		C=0;
		D=0;
		#period;

		A=0;
		B=0;
		C=0;
		D=1;
		#period;

		A=0;
		B=0;
		C=1;
		D=0;
		#period;

		A=0;
		B=0;
		C=1;
		D=1;
		#period;

		A=0;
		B=1;
		C=0;
		D=0;
		#period;

		A=0;
		B=1;
		C=0;
		D=1;
		#period;

		A=0;
		B=1;
		C=1;
		D=0;
		#period;

		A=0;
		B=1;
		C=1;
		D=1;
		#period;

		A=1;
		B=0;
		C=0;
		D=0;
		#period;

		A=1;
		B=0;
		C=0;
		D=1;
		#period;

		A=1;
		B=0;
		C=1;
		D=0;
		#period;

		A=1;
		B=0;
		C=1;
		D=1;
		#period;

		A=1;
		B=1;
		C=0;
		D=0;
		#period;

		A=1;
		B=1;
		C=0;
		D=1;
		#period;

		A=1;
		B=1;
		C=1;
		D=0;
		#period;

		A=1;
		B=1;
		C=1;
		D=1;
		#period;
	end
	initial #300 $finish;
	//dump the result of simulation
	initial begin
		$dumpfile("Lab1.vcd");
		$dumpvars;
	end
endmodule

Lab1/Lab1.vcd
$date
	Tue Apr 19 16:41:56 2022
$end
$version
	Icarus Verilog
$end
$timescale
	1s
$end
$scope module t_Lab1 $end
$var wire 1 ! F3 $end
$var wire 1 " F2 $end
$var wire 1 # F1 $end
$var reg 1 $ A $end
$var reg 1 % B $end
$var reg 1 & C $end
$var reg 1 ' D $end
$scope module Dataflow $end
$var wire 1 $ A $end
$var wire 1 % B $end
$var wire 1 & C $end
$var wire 1 ' D $end
$var wire 1 " F $end
$var wire 1 ( w1 $end
$var wire 1 ) w2 $end
$var wire 1 * w3 $end
$var wire 1 + w4 $end
$var wire 1 , w5 $end
$var wire 1 - w6 $end
$var wire 1 . w7 $end
$upscope $end
$scope module Gatelevel $end
$var wire 1 $ A $end
$var wire 1 % B $end
$var wire 1 & C $end
$var wire 1 ' D $end
$var wire 1 # F $end
$var wire 1 / w1 $end
$var wire 1 0 w2 $end
$var wire 1 1 w3 $end
$var wire 1 2 w4 $end
$var wire 1 3 w5 $end
$var wire 1 4 w6 $end
$var wire 1 5 w7 $end
$upscope $end
$scope module UDP $end
$var wire 1 $ A $end
$var wire 1 % B $end
$var wire 1 & C $end
$var wire 1 ' D $end
$var wire 1 ! F $end
$var wire 1 6 w1 $end
$var wire 1 7 w3 $end
$var wire 1 8 w4 $end
$var wire 1 9 w5 $end
$var wire 1 : w7 $end
$upscope $end
$upscope $end
$enddefinitions $end
#0
$dumpvars
0:
19
08
07
16
05
14
13
02
01
10
1/
0.
1-
1,
0+
0*
1)
1(
0'
0&
0%
0$
0#
0"
0!
$end
#20
0-
04
0,
03
09
1'
#40
1-
14
1"
1#
1!
1,
13
19
1*
11
17
0'
1&
#60
0-
04
0,
03
09
1'
#80
1-
14
0"
0#
0!
0)
00
1,
13
19
0*
01
07
0(
0/
06
0'
0&
1%
#100
0-
04
0,
03
09
1'
#120
1-
14
1,
13
19
1+
12
18
0'
1&
#140
0,
03
09
1'
#160
1"
1#
1!
1,
13
19
1(
0+
1/
02
16
08
1)
1.
10
15
1:
0'
0&
0%
1$
#180
0"
0#
0.
05
0!
0-
04
0:
0,
03
09
1'
#200
1.
15
1-
14
1:
1"
1#
1!
1,
13
19
1*
11
17
0'
1&
#220
0.
05
0-
04
0:
0,
03
09
1'
#240
1.
15
1-
14
1:
1"
1#
1!
1,
13
19
0*
01
07
0(
0/
06
0'
0&
1%
#260
0"
0#
0.
05
0!
0-
04
0:
0,
03
09
1'
#280
1.
15
1"
1-
1#
14
1!
1:
1,
13
19
1*
1+
11
12
17
18
0'
1&
#300
0,
03
09
1'
